diagnose/__init__.py
diagnose/arguments.py
diagnose/arguments.yaml
diagnose/client.py
diagnose/diag.py
diagnose/diagnostic_report.py
diagnose/ecs.py
diagnose/exceptions.py
diagnose/logger_config.py
diagnose/notification_template.py
diagnose/redis_instance.py
diagnose/sdk.py
diagnose/utils.py
redis_diagnose_tool-0.1.2.dist-info/LICENSE
redis_diagnose_tool-0.1.2.dist-info/METADATA
redis_diagnose_tool-0.1.2.dist-info/WHEEL
redis_diagnose_tool-0.1.2.dist-info/entry_points.txt
redis_diagnose_tool-0.1.2.dist-info/top_level.txt
redis_diagnose_tool-0.1.2.dist-info/RECORD
