Metadata-Version: 2.1
Name: redis-diagnose-tool
Version: 0.1.2
Summary: redis-diagnose-tool is a tool for diagnosing Redis/Tair client connection errors.
Home-page: https://github.com/tair-opensource/tair-tools/tree/main/redis-diagnose-tool
License: MIT
Classifier: Programming Language :: Python :: 3
Classifier: License :: OSI Approved :: MIT License
Classifier: Operating System :: OS Independent
Requires-Python: >=3.6
License-File: LICENSE
Requires-Dist: PyYAML >=6.0.1
Requires-Dist: redis >=4.3.0
Requires-Dist: psutil >=6.0.0
Requires-Dist: distro >=1.9.0
Requires-Dist: requests >=2.27.1
Requires-Dist: python-dateutil >=2.9.0
Requires-Dist: colorlog >=6.8.2
Requires-Dist: alibabacloud-r-kvstore20150101 >=4.2.0
Requires-Dist: alibabacloud-ecs20140526 >=4.1.8
Requires-Dist: tqdm >=4.63.0
